glad/__init__.py
glad/__main__.py
glad/config.py
glad/opener.py
glad/parse.py
glad/plugin.py
glad/sink.py
glad/specification.py
glad/util.py
glad/files/__init__.py
glad/files/egl.xml
glad/files/eglplatform.h
glad/files/gl.xml
glad/files/glx.xml
glad/files/khrplatform.h
glad/files/vk.xml
glad/files/vk_platform.h
glad/files/vulkan_video_codec_av1std.h
glad/files/vulkan_video_codec_av1std_decode.h
glad/files/vulkan_video_codec_h264std.h
glad/files/vulkan_video_codec_h264std_decode.h
glad/files/vulkan_video_codec_h264std_encode.h
glad/files/vulkan_video_codec_h265std.h
glad/files/vulkan_video_codec_h265std_decode.h
glad/files/vulkan_video_codec_h265std_encode.h
glad/files/vulkan_video_codecs_common.h
glad/files/wgl.xml
glad/generator/__init__.py
glad/generator/util.py
glad/generator/c/__init__.py
glad/generator/c/templates/base_template.c
glad/generator/c/templates/base_template.h
glad/generator/c/templates/egl.c
glad/generator/c/templates/egl.h
glad/generator/c/templates/gl.c
glad/generator/c/templates/gl.h
glad/generator/c/templates/glx.c
glad/generator/c/templates/glx.h
glad/generator/c/templates/header_only.h
glad/generator/c/templates/impl_util.c
glad/generator/c/templates/platform.h
glad/generator/c/templates/template_utils.h
glad/generator/c/templates/vk.c
glad/generator/c/templates/vk.h
glad/generator/c/templates/wgl.c
glad/generator/c/templates/wgl.h
glad/generator/c/templates/loader/egl.c
glad/generator/c/templates/loader/egl.h
glad/generator/c/templates/loader/gl.c
glad/generator/c/templates/loader/gl.h
glad/generator/c/templates/loader/gles1.c
glad/generator/c/templates/loader/gles1.h
glad/generator/c/templates/loader/gles2.c
glad/generator/c/templates/loader/gles2.h
glad/generator/c/templates/loader/glsc2.c
glad/generator/c/templates/loader/glsc2.h
glad/generator/c/templates/loader/glx.c
glad/generator/c/templates/loader/glx.h
glad/generator/c/templates/loader/library.c
glad/generator/c/templates/loader/vulkan.c
glad/generator/c/templates/loader/vulkan.h
glad2-2.0.8.dist-info/LICENSE
glad2-2.0.8.dist-info/METADATA
glad2-2.0.8.dist-info/WHEEL
glad2-2.0.8.dist-info/entry_points.txt
glad2-2.0.8.dist-info/top_level.txt
glad2-2.0.8.dist-info/RECORD
