Metadata-Version: 2.1
Name: glad2
Version: 2.0.8
Summary: Multi-Language GL/GLES/EGL/GLX/VK/WGL Loader-Generator based on the official specifications.
Author-email: David Herberth <github@dav1d.de>
Maintainer-email: David Herberth <github@dav1d.de>
License: The glad source code:
Project-URL: Source, https://github.com/Dav1dde/glad
Keywords: opengl,glad,generator,gl,wgl,egl,gles,vulkan,vk,glx
Platform: any
Classifier: Development Status :: 5 - Production/Stable
Classifier: Environment :: Console
Classifier: Intended Audience :: Developers
Classifier: Intended Audience :: Education
Classifier: Intended Audience :: Science/Research
Classifier: License :: OSI Approved :: MIT License
Classifier: Natural Language :: English
Classifier: Operating System :: OS Independent
Classifier: Programming Language :: Python :: 3
Classifier: Programming Language :: Python :: 3.8
Classifier: Programming Language :: Python :: 3.9
Classifier: Programming Language :: Python :: 3.10
Classifier: Programming Language :: Python :: 3.11
Classifier: Programming Language :: Python :: 3.12
Classifier: Topic :: Games/Entertainment
Classifier: Topic :: Multimedia :: Graphics
Classifier: Topic :: Multimedia :: Graphics :: 3D Rendering
Classifier: Topic :: Software Development
Classifier: Topic :: Software Development :: Build Tools
Classifier: Topic :: Utilities
License-File: LICENSE
Requires-Dist: Jinja2 <4.0,>=2.7
Provides-Extra: fortran
Requires-Dist: glad2-fortran ; extra == 'fortran'
